{
  "generator-jhipster": {
    "jhipsterVersion": "3.1.0",
    "baseName": "archinotesx",
    "packageName": "com.uniandes.thesis",
    "packageFolder": "com/uniandes/thesis",
    "serverPort": "8080",
    "authenticationType": "jwt",
    "hibernateCache": "ehcache",
    "clusteredHttpSession": "no",
    "websocket": "no",
    "databaseType": "sql",
    "devDatabaseType": "mysql",
	"testDatabaseType": "mysql",
    "prodDatabaseType": "mysql",
    "searchEngine": "no",
    "buildTool": "maven",
    "enableSocialSignIn": false,
    "jwtSecretKey": "3b666e9dfcb4b79c5afab5ab57fc4f29da68db4a",
    "useSass": false,
    "applicationType": "monolith",
    "testFrameworks": [
      "gatling",
      "cucumber",
      "protractor"
    ],
    "jhiPrefix": "jhi",
    "enableTranslation": false
  }
}
